odoo10_addon_medical-10.0.1.1.0-py2.7-nspkg.pth
odoo/addons/medical/README.rst
odoo/addons/medical/__init__.py
odoo/addons/medical/__manifest__.py
odoo/addons/medical/data/ir_sequence_data.xml
odoo/addons/medical/demo/medical_patient_demo.xml
odoo/addons/medical/i18n/es_CO.po
odoo/addons/medical/i18n/fr.po
odoo/addons/medical/i18n/nl_NL.po
odoo/addons/medical/i18n/pt_BR.po
odoo/addons/medical/i18n/ro.po
odoo/addons/medical/models/__init__.py
odoo/addons/medical/models/medical_abstract_entity.py
odoo/addons/medical/models/medical_patient.py
odoo/addons/medical/models/res_partner.py
odoo/addons/medical/security/ir.model.access.csv
odoo/addons/medical/security/medical_security.xml
odoo/addons/medical/static/description/icon.png
odoo/addons/medical/static/src/img/patient-avatar.png
odoo/addons/medical/static/src/js/medical.tour.js
odoo/addons/medical/templates/assets.xml
odoo/addons/medical/tests/__init__.py
odoo/addons/medical/tests/test_medical_patient.py
odoo/addons/medical/tests/test_res_partner.py
odoo/addons/medical/views/medical_abstract_entity.xml
odoo/addons/medical/views/medical_menu.xml
odoo/addons/medical/views/medical_patient.xml
odoo/addons/medical/views/res_partner.xml
odoo10_addon_medical-10.0.1.1.0.dist-info/DESCRIPTION.rst
odoo10_addon_medical-10.0.1.1.0.dist-info/METADATA
odoo10_addon_medical-10.0.1.1.0.dist-info/RECORD
odoo10_addon_medical-10.0.1.1.0.dist-info/WHEEL
odoo10_addon_medical-10.0.1.1.0.dist-info/metadata.json
odoo10_addon_medical-10.0.1.1.0.dist-info/namespace_packages.txt
odoo10_addon_medical-10.0.1.1.0.dist-info/top_level.txt
